MANIFEST.in
README.md
development.ini
production.ini
setup.cfg
setup.py
pyramid_oauth2_provider/__init__.py
pyramid_oauth2_provider/authentication.py
pyramid_oauth2_provider/errors.py
pyramid_oauth2_provider/generators.py
pyramid_oauth2_provider/interfaces.py
pyramid_oauth2_provider/jsonerrors.py
pyramid_oauth2_provider/models.py
pyramid_oauth2_provider/tests.py
pyramid_oauth2_provider/util.py
pyramid_oauth2_provider/views.py
pyramid_oauth2_provider.egg-info/PKG-INFO
pyramid_oauth2_provider.egg-info/SOURCES.txt
pyramid_oauth2_provider.egg-info/dependency_links.txt
pyramid_oauth2_provider.egg-info/entry_points.txt
pyramid_oauth2_provider.egg-info/not-zip-safe
pyramid_oauth2_provider.egg-info/requires.txt
pyramid_oauth2_provider.egg-info/top_level.txt
pyramid_oauth2_provider/scripts/__init__.py
pyramid_oauth2_provider/scripts/create_client_credentials.py
pyramid_oauth2_provider/scripts/initializedb.py