Metadata-Version: 1.1
Name: pyramid_oauth2_provider
Version: 0.2
Summary: Oauth2 endpoint for pyramid applications
Home-page: http://github.com/elliotpeele/pyramid_oauth2_provider
Author: Elliot Peele
Author-email: elliot@bentlogic.net
License: UNKNOWN
Keywords: web wsgi bfg pylons pyramid oauth2
Platform: UNKNOWN
Classifier: Programming Language :: Python
Classifier: Framework :: Pyramid
Classifier: Topic :: Internet :: WWW/HTTP
Classifier: Topic :: Internet :: WWW/HTTP :: WSGI :: Application
